{"yellow_trips_df": {"module": "pandas.core.frame", "name": "DataFrame", "type": "instance", "uuid": "pandas.core.frame.DataFrame", "hash": "0x7b1dd3d21240", "variable_type": "dataframe"}, "green_trips_df": {"module": "pandas.core.frame", "name": "DataFrame", "type": "instance", "uuid": "pandas.core.frame.DataFrame", "hash": "0x7b1dd3d21cc0", "variable_type": "dataframe"}, "zones_df": {"module": "pandas.core.frame", "name": "DataFrame", "type": "instance", "uuid": "pandas.core.frame.DataFrame", "hash": "0x7b1dd3d3a800", "variable_type": "dataframe"}, "audit_df": {"module": "pandas.core.frame", "name": "DataFrame", "type": "instance", "uuid": "pandas.core.frame.DataFrame", "hash": "0x7b1dd3d2fa90", "variable_type": "dataframe"}}